pdfquery/__init__.py
pdfquery/cache.py
pdfquery/pdfquery.py
pdfquery/pdftranslator.py
tests/__init__.py
tests/test_main.py
tests/utils.py
totopdfquery/__init__.py
totopdfquery/cache.py
totopdfquery/pdftranslator.py
totopdfquery/totopdfquery.py
toto_pdfquery-0.1.3.dist-info/LICENSE.txt
toto_pdfquery-0.1.3.dist-info/METADATA
toto_pdfquery-0.1.3.dist-info/WHEEL
toto_pdfquery-0.1.3.dist-info/top_level.txt
toto_pdfquery-0.1.3.dist-info/RECORD
