Metadata-Version: 2.1
Name: toto-pdfquery
Version: 0.1.3
Summary: Concise and friendly PDF scraper using JQuery or XPath selectors. Forked from Jack Cushman's pdfquery as not maintained anymore.
Home-page: https://github.com/nicolasances/pdfquery
Author: Jack Cushman
Author-email: jcushman@gmail.com
License: MIT
Platform: UNKNOWN
Classifier: Development Status :: 4 - Beta
Classifier: Topic :: Text Processing
Classifier: Topic :: Utilities
Classifier: License :: OSI Approved :: MIT License
Classifier: Intended Audience :: Developers
Classifier: Operating System :: OS Independent
Classifier: Programming Language :: Python
Classifier: Programming Language :: Python :: 2
Classifier: Programming Language :: Python :: 2.6
Classifier: Programming Language :: Python :: 2.7
Classifier: Programming Language :: Python :: 3
Classifier: Programming Language :: Python :: 3.3
Classifier: Programming Language :: Python :: 3.4
Classifier: Programming Language :: Python :: 3.5
License-File: LICENSE.txt
Requires-Dist: cssselect >=0.7.1
Requires-Dist: chardet
Requires-Dist: lxml >=3.0
Requires-Dist: pdfminer.six
Requires-Dist: pyquery >=1.2.2
Requires-Dist: roman >=1.4.0
